CasseySmithCV/ReadFiles.py
CasseySmithCV/Simulation.py
CasseySmithCV/__init__.py
casseysmithcv-0.1.0.dist-info/METADATA
casseysmithcv-0.1.0.dist-info/WHEEL
casseysmithcv-0.1.0.dist-info/licenses/LICENSE
casseysmithcv-0.1.0.dist-info/RECORD
