Metadata-Version: 2.1
Name: CasseySmithCV
Version: 0.1.0
Summary: Produces critical values using the methods described in Cassey Smith (2014).  Code is modernized from version published with paper to take advantage of advances in computing.
Project-URL: Homepage, https://github.com/tazzben/CasseySmithCV
Project-URL: Bug Tracker, https://github.com/tazzben/CasseySmithCV/issues
Author-email: Ben Smith <bosmith@unomaha.edu>
Maintainer-email: Ben Smith <bosmith@unomaha.edu>
License-Expression: MIT
License-File: LICENSE
Keywords: EG Statistic,Monte Carlo,Statistics
Classifier: Development Status :: 5 - Production/Stable
Classifier: Intended Audience :: Science/Research
Classifier: License :: OSI Approved :: MIT License
Classifier: Programming Language :: Python :: 3.8
Classifier: Programming Language :: Python :: 3.9
Classifier: Programming Language :: Python :: 3.10
Classifier: Programming Language :: Python :: 3.11
Requires-Python: >=3.8
Requires-Dist: numpy>=1.21.0
Requires-Dist: pandas>=1.3.0
Requires-Dist: tqdm>=4.26.0
